{"id":105,"name":"سُورَةُ الفِيلِ","revelationType":"Meccan","numberOfAyahs":5,"pages":[601],"ayahs":[{"number":6189,"numberInSurah":1,"text":"أَلَمْ تَرَ كَيْفَ فَعَلَ رَبُّكَ بِأَصْحَـٰبِ ٱلْفِيلِ","page":601,"sajda":null,"words":[{"c":"ﮍ","p":601,"l":13},{"c":"ﮎ","p":601,"l":13},{"c":"ﮏ","p":601,"l":13},{"c":"ﮐ","p":601,"l":13},{"c":"ﮑ","p":601,"l":13},{"c":"ﮒ","p":601,"l":13},{"c":"ﮓ","p":601,"l":13},{"c":"ﮔ","p":601,"l":13,"t":"end"}]},{"number":6190,"numberInSurah":2,"text":"أَلَمْ يَجْعَلْ كَيْدَهُمْ فِى تَضْلِيلٍ","page":601,"sajda":null,"words":[{"c":"ﮕ","p":601,"l":13},{"c":"ﮖ","p":601,"l":13},{"c":"ﮗ","p":601,"l":13},{"c":"ﮘ","p":601,"l":14},{"c":"ﮙ","p":601,"l":14},{"c":"ﮚ","p":601,"l":14,"t":"end"}]},{"number":6191,"numberInSurah":3,"text":"وَأَرْسَلَ عَلَيْهِمْ طَيْرًا أَبَابِيلَ","page":601,"sajda":null,"words":[{"c":"ﮛ","p":601,"l":14},{"c":"ﮜ","p":601,"l":14},{"c":"ﮝ","p":601,"l":14},{"c":"ﮞ","p":601,"l":14},{"c":"ﮟ","p":601,"l":14,"t":"end"}]},{"number":6192,"numberInSurah":4,"text":"تَرْمِيهِم بِحِجَارَةٍ مِّن سِجِّيلٍ","page":601,"sajda":null,"words":[{"c":"ﮠ","p":601,"l":14},{"c":"ﮡ","p":601,"l":15},{"c":"ﮢ","p":601,"l":15},{"c":"ﮣ","p":601,"l":15},{"c":"ﮤ","p":601,"l":15,"t":"end"}]},{"number":6193,"numberInSurah":5,"text":"فَجَعَلَهُمْ كَعَصْفٍ مَّأْكُولٍۭ","page":601,"sajda":null,"words":[{"c":"ﮥ","p":601,"l":15},{"c":"ﮦ","p":601,"l":15},{"c":"ﮧ","p":601,"l":15},{"c":"ﮨ","p":601,"l":15,"t":"end"}]}]}